apiogram/__init__.py
apiogram/bot.py
apiogram/direction.py
apiogram/helpers/__init__.py
apiogram/helpers/middleware/__init__.py
apiogram/helpers/middleware/msglogger.py
apiogram/models/__init__.py
apiogram/models/user/__init__.py
apiogram/models/user/asyn.py
apiogram-0.2.2.dist-info/LICENSE
apiogram-0.2.2.dist-info/METADATA
apiogram-0.2.2.dist-info/WHEEL
apiogram-0.2.2.dist-info/top_level.txt
apiogram-0.2.2.dist-info/RECORD
